[
  {
    "accessionNumber":"0000000000-22-009320",
    "filingDate":"2022-08-29T00:00:00.000",
    "acceptanceDateTime":"2022-08-29T09:30:03.000Z",
    "form":"UPLOAD",
    "fileNumber":"",
    "primaryDocument":"filename1.pdf",
    "primaryDocDescription":"",
    "isXBRL":0,
    "isInlineXBRL":0,
    "source_file":"company_submissions.json",
    "normalized_form":"STAFF_LETTER",
    "form_role":"event_anchor",
    "ticker":"OKE",
    "cik":"0001039684",
    "firm_name":"Oneok",
    "industry":"Energy",
    "thread_id":"OKE_0000000000-22-009320",
    "qa_status":"thread_anchor",
    "document_name":"filename1.pdf",
    "document_url":"https:\/\/www.sec.gov\/Archives\/edgar\/data\/1039684\/000000000022009320\/filename1.pdf",
    "raw_document_path":"data\/raw\/sec\/OKE\/OKE_0000000000-22-009320\/filings\/0000000000-22-009320\/filename1.pdf",
    "extracted_text_path":"data\/raw\/sec\/OKE\/OKE_0000000000-22-009320\/extracted_text\/0000000000-22-009320.txt",
    "extraction_status":"ok",
    "letter_word_count_file":671
  },
  {
    "accessionNumber":"0001193125-22-242112",
    "filingDate":"2022-09-09T00:00:00.000",
    "acceptanceDateTime":"2022-09-09T18:18:00.000Z",
    "form":"CORRESP",
    "fileNumber":"",
    "primaryDocument":"filename1.htm",
    "primaryDocDescription":"",
    "isXBRL":0,
    "isInlineXBRL":0,
    "source_file":"company_submissions.json",
    "normalized_form":"FILER_RESPONSE",
    "form_role":"thread_context",
    "ticker":"OKE",
    "cik":"0001039684",
    "firm_name":"Oneok",
    "industry":"Energy",
    "thread_id":"OKE_0000000000-22-009320",
    "qa_status":"matched",
    "document_name":"filename1.htm",
    "document_url":"https:\/\/www.sec.gov\/Archives\/edgar\/data\/1039684\/000119312522242112\/filename1.htm",
    "raw_document_path":"data\/raw\/sec\/OKE\/OKE_0000000000-22-009320\/filings\/0001193125-22-242112\/filename1.htm",
    "extracted_text_path":"data\/raw\/sec\/OKE\/OKE_0000000000-22-009320\/extracted_text\/0001193125-22-242112.txt",
    "extraction_status":"ok",
    "letter_word_count_file":2364
  },
  {
    "accessionNumber":"0000000000-22-010439",
    "filingDate":"2022-09-22T00:00:00.000",
    "acceptanceDateTime":"2022-09-22T11:30:03.000Z",
    "form":"UPLOAD",
    "fileNumber":"",
    "primaryDocument":"filename1.pdf",
    "primaryDocDescription":"",
    "isXBRL":0,
    "isInlineXBRL":0,
    "source_file":"company_submissions.json",
    "normalized_form":"STAFF_LETTER",
    "form_role":"event_anchor",
    "ticker":"OKE",
    "cik":"0001039684",
    "firm_name":"Oneok",
    "industry":"Energy",
    "thread_id":"OKE_0000000000-22-009320",
    "qa_status":"matched_followup_staff_letter",
    "document_name":"filename1.pdf",
    "document_url":"https:\/\/www.sec.gov\/Archives\/edgar\/data\/1039684\/000000000022010439\/filename1.pdf",
    "raw_document_path":"data\/raw\/sec\/OKE\/OKE_0000000000-22-009320\/filings\/0000000000-22-010439\/filename1.pdf",
    "extracted_text_path":"data\/raw\/sec\/OKE\/OKE_0000000000-22-009320\/extracted_text\/0000000000-22-010439.txt",
    "extraction_status":"ok",
    "letter_word_count_file":331
  },
  {
    "accessionNumber":"0001193125-22-264068",
    "filingDate":"2022-10-18T00:00:00.000",
    "acceptanceDateTime":"2022-10-18T06:05:28.000Z",
    "form":"CORRESP",
    "fileNumber":"",
    "primaryDocument":"filename1.htm",
    "primaryDocDescription":"",
    "isXBRL":0,
    "isInlineXBRL":0,
    "source_file":"company_submissions.json",
    "normalized_form":"FILER_RESPONSE",
    "form_role":"thread_context",
    "ticker":"OKE",
    "cik":"0001039684",
    "firm_name":"Oneok",
    "industry":"Energy",
    "thread_id":"OKE_0000000000-22-009320",
    "qa_status":"matched",
    "document_name":"filename1.htm",
    "document_url":"https:\/\/www.sec.gov\/Archives\/edgar\/data\/1039684\/000119312522264068\/filename1.htm",
    "raw_document_path":"data\/raw\/sec\/OKE\/OKE_0000000000-22-009320\/filings\/0001193125-22-264068\/filename1.htm",
    "extracted_text_path":"data\/raw\/sec\/OKE\/OKE_0000000000-22-009320\/extracted_text\/0001193125-22-264068.txt",
    "extraction_status":"ok",
    "letter_word_count_file":248
  },
  {
    "accessionNumber":"0001193125-22-266588",
    "filingDate":"2022-10-21T00:00:00.000",
    "acceptanceDateTime":"2022-10-21T13:06:29.000Z",
    "form":"CORRESP",
    "fileNumber":"",
    "primaryDocument":"filename1.htm",
    "primaryDocDescription":"",
    "isXBRL":0,
    "isInlineXBRL":0,
    "source_file":"company_submissions.json",
    "normalized_form":"FILER_RESPONSE",
    "form_role":"thread_context",
    "ticker":"OKE",
    "cik":"0001039684",
    "firm_name":"Oneok",
    "industry":"Energy",
    "thread_id":"OKE_0000000000-22-009320",
    "qa_status":"matched",
    "document_name":"filename1.htm",
    "document_url":"https:\/\/www.sec.gov\/Archives\/edgar\/data\/1039684\/000119312522266588\/filename1.htm",
    "raw_document_path":"data\/raw\/sec\/OKE\/OKE_0000000000-22-009320\/filings\/0001193125-22-266588\/filename1.htm",
    "extracted_text_path":"data\/raw\/sec\/OKE\/OKE_0000000000-22-009320\/extracted_text\/0001193125-22-266588.txt",
    "extraction_status":"ok",
    "letter_word_count_file":824
  },
  {
    "accessionNumber":"0000000000-22-011909",
    "filingDate":"2022-11-01T00:00:00.000",
    "acceptanceDateTime":"2022-11-01T15:30:03.000Z",
    "form":"UPLOAD",
    "fileNumber":"",
    "primaryDocument":"filename1.pdf",
    "primaryDocDescription":"",
    "isXBRL":0,
    "isInlineXBRL":0,
    "source_file":"company_submissions.json",
    "normalized_form":"STAFF_LETTER",
    "form_role":"event_anchor",
    "ticker":"OKE",
    "cik":"0001039684",
    "firm_name":"Oneok",
    "industry":"Energy",
    "thread_id":"OKE_0000000000-22-009320",
    "qa_status":"matched_followup_staff_letter",
    "document_name":"filename1.pdf",
    "document_url":"https:\/\/www.sec.gov\/Archives\/edgar\/data\/1039684\/000000000022011909\/filename1.pdf",
    "raw_document_path":"data\/raw\/sec\/OKE\/OKE_0000000000-22-009320\/filings\/0000000000-22-011909\/filename1.pdf",
    "extracted_text_path":"data\/raw\/sec\/OKE\/OKE_0000000000-22-009320\/extracted_text\/0000000000-22-011909.txt",
    "extraction_status":"ok",
    "letter_word_count_file":100
  }
]