{
  "directory": {
    "item": [
      {
        "last-modified": "2019-02-14 09:27:18",
        "name": "0001140361-19-003105-index-headers.html",
        "type": "text.gif",
        "size": ""
      },
      {
        "last-modified": "2019-02-14 09:27:18",
        "name": "0001140361-19-003105-index.html",
        "type": "text.gif",
        "size": ""
      },
      {
        "last-modified": "2019-02-14 09:27:18",
        "name": "0001140361-19-003105.txt",
        "type": "text.gif",
        "size": ""
      },
      {
        "last-modified": "2019-02-14 09:27:18",
        "name": "filename1.htm",
        "type": "text.gif",
        "size": "23509"
      },
      {
        "last-modified": "2019-02-14 09:27:18",
        "name": "s002479x3_image01.jpg",
        "type": "image2.gif",
        "size": "5253"
      }
    ],
    "name": "/Archives/edgar/data/202058/000114036119003105",
    "parent-dir": "/Archives/edgar/data/202058"
  }
}