{
  "directory": {
    "item": [
      {
        "last-modified": "2017-06-07 12:50:41",
        "name": "0000000000-17-019850-index-headers.html",
        "type": "text.gif",
        "size": ""
      },
      {
        "last-modified": "2017-06-07 12:50:41",
        "name": "0000000000-17-019850-index.html",
        "type": "text.gif",
        "size": ""
      },
      {
        "last-modified": "2017-06-07 12:50:41",
        "name": "0000000000-17-019850.txt",
        "type": "text.gif",
        "size": ""
      },
      {
        "last-modified": "2017-06-07 12:50:41",
        "name": "filename1.pdf",
        "type": "",
        "size": "42512"
      }
    ],
    "name": "/Archives/edgar/data/899051/000000000017019850",
    "parent-dir": "/Archives/edgar/data/899051"
  }
}