{
  "directory": {
    "item": [
      {
        "last-modified": "2022-10-04 12:01:06",
        "name": "0001104659-22-105695-index-headers.html",
        "type": "text.gif",
        "size": ""
      },
      {
        "last-modified": "2022-10-04 12:01:06",
        "name": "0001104659-22-105695-index.html",
        "type": "text.gif",
        "size": ""
      },
      {
        "last-modified": "2022-10-04 12:01:06",
        "name": "0001104659-22-105695.txt",
        "type": "text.gif",
        "size": ""
      },
      {
        "last-modified": "2022-10-04 12:01:06",
        "name": "filename1.htm",
        "type": "text.gif",
        "size": "16945"
      },
      {
        "last-modified": "2022-10-04 12:01:06",
        "name": "tm2227344d1_correspimg001.jpg",
        "type": "image2.gif",
        "size": "12085"
      }
    ],
    "name": "/Archives/edgar/data/1551152/000110465922105695",
    "parent-dir": "/Archives/edgar/data/1551152"
  }
}