{
  "directory": {
    "item": [
      {
        "last-modified": "2018-04-17 15:51:18",
        "name": "0000000000-18-011647-index-headers.html",
        "type": "text.gif",
        "size": ""
      },
      {
        "last-modified": "2018-04-17 15:51:18",
        "name": "0000000000-18-011647-index.html",
        "type": "text.gif",
        "size": ""
      },
      {
        "last-modified": "2018-04-17 15:51:18",
        "name": "0000000000-18-011647.txt",
        "type": "text.gif",
        "size": ""
      },
      {
        "last-modified": "2018-04-17 15:51:18",
        "name": "filename1.pdf",
        "type": "",
        "size": "33200"
      }
    ],
    "name": "/Archives/edgar/data/37996/000000000018011647",
    "parent-dir": "/Archives/edgar/data/37996"
  }
}