[
  {
    "accessionNumber":"0000000000-16-094772",
    "filingDate":"2016-09-27T00:00:00.000",
    "acceptanceDateTime":"2016-09-27T19:59:14.000Z",
    "form":"UPLOAD",
    "fileNumber":"",
    "primaryDocument":"filename1.pdf",
    "primaryDocDescription":"",
    "isXBRL":0,
    "isInlineXBRL":0,
    "source_file":"company_submissions.json",
    "normalized_form":"STAFF_LETTER",
    "form_role":"event_anchor",
    "ticker":"MDLZ",
    "cik":"0001103982",
    "firm_name":"Mondelez International",
    "industry":"Consumer Staples",
    "thread_id":"MDLZ_0000000000-16-094772",
    "qa_status":"thread_anchor",
    "document_name":"filename1.pdf",
    "document_url":"https:\/\/www.sec.gov\/Archives\/edgar\/data\/1103982\/000000000016094772\/filename1.pdf",
    "raw_document_path":"data\/raw\/sec\/MDLZ\/MDLZ_0000000000-16-094772\/filings\/0000000000-16-094772\/filename1.pdf",
    "extracted_text_path":"data\/raw\/sec\/MDLZ\/MDLZ_0000000000-16-094772\/extracted_text\/0000000000-16-094772.txt",
    "extraction_status":"ok",
    "letter_word_count_file":468
  },
  {
    "accessionNumber":"0001193125-16-733863",
    "filingDate":"2016-10-07T00:00:00.000",
    "acceptanceDateTime":"2016-10-07T20:41:55.000Z",
    "form":"CORRESP",
    "fileNumber":"",
    "primaryDocument":"filename1.htm",
    "primaryDocDescription":"",
    "isXBRL":0,
    "isInlineXBRL":0,
    "source_file":"company_submissions.json",
    "normalized_form":"FILER_RESPONSE",
    "form_role":"thread_context",
    "ticker":"MDLZ",
    "cik":"0001103982",
    "firm_name":"Mondelez International",
    "industry":"Consumer Staples",
    "thread_id":"MDLZ_0000000000-16-094772",
    "qa_status":"matched",
    "document_name":"filename1.htm",
    "document_url":"https:\/\/www.sec.gov\/Archives\/edgar\/data\/1103982\/000119312516733863\/filename1.htm",
    "raw_document_path":"data\/raw\/sec\/MDLZ\/MDLZ_0000000000-16-094772\/filings\/0001193125-16-733863\/filename1.htm",
    "extracted_text_path":"data\/raw\/sec\/MDLZ\/MDLZ_0000000000-16-094772\/extracted_text\/0001193125-16-733863.txt",
    "extraction_status":"ok",
    "letter_word_count_file":1094
  },
  {
    "accessionNumber":"0000000000-16-106394",
    "filingDate":"2016-12-23T00:00:00.000",
    "acceptanceDateTime":"2016-12-23T16:53:37.000Z",
    "form":"UPLOAD",
    "fileNumber":"",
    "primaryDocument":"filename1.pdf",
    "primaryDocDescription":"",
    "isXBRL":0,
    "isInlineXBRL":0,
    "source_file":"company_submissions.json",
    "normalized_form":"STAFF_LETTER",
    "form_role":"event_anchor",
    "ticker":"MDLZ",
    "cik":"0001103982",
    "firm_name":"Mondelez International",
    "industry":"Consumer Staples",
    "thread_id":"MDLZ_0000000000-16-094772",
    "qa_status":"matched_followup_staff_letter",
    "document_name":"filename1.pdf",
    "document_url":"https:\/\/www.sec.gov\/Archives\/edgar\/data\/1103982\/000000000016106394\/filename1.pdf",
    "raw_document_path":"data\/raw\/sec\/MDLZ\/MDLZ_0000000000-16-094772\/filings\/0000000000-16-106394\/filename1.pdf",
    "extracted_text_path":"data\/raw\/sec\/MDLZ\/MDLZ_0000000000-16-094772\/extracted_text\/0000000000-16-106394.txt",
    "extraction_status":"ok",
    "letter_word_count_file":340
  },
  {
    "accessionNumber":"0001193125-17-002403",
    "filingDate":"2017-01-05T00:00:00.000",
    "acceptanceDateTime":"2017-01-05T12:34:32.000Z",
    "form":"CORRESP",
    "fileNumber":"",
    "primaryDocument":"filename1.htm",
    "primaryDocDescription":"",
    "isXBRL":0,
    "isInlineXBRL":0,
    "source_file":"company_submissions.json",
    "normalized_form":"FILER_RESPONSE",
    "form_role":"thread_context",
    "ticker":"MDLZ",
    "cik":"0001103982",
    "firm_name":"Mondelez International",
    "industry":"Consumer Staples",
    "thread_id":"MDLZ_0000000000-16-094772",
    "qa_status":"matched",
    "document_name":"filename1.htm",
    "document_url":"https:\/\/www.sec.gov\/Archives\/edgar\/data\/1103982\/000119312517002403\/filename1.htm",
    "raw_document_path":"data\/raw\/sec\/MDLZ\/MDLZ_0000000000-16-094772\/filings\/0001193125-17-002403\/filename1.htm",
    "extracted_text_path":"data\/raw\/sec\/MDLZ\/MDLZ_0000000000-16-094772\/extracted_text\/0001193125-17-002403.txt",
    "extraction_status":"ok",
    "letter_word_count_file":543
  },
  {
    "accessionNumber":"0000000000-17-003205",
    "filingDate":"2017-01-30T00:00:00.000",
    "acceptanceDateTime":"2017-01-30T20:41:20.000Z",
    "form":"UPLOAD",
    "fileNumber":"",
    "primaryDocument":"filename1.pdf",
    "primaryDocDescription":"",
    "isXBRL":0,
    "isInlineXBRL":0,
    "source_file":"company_submissions.json",
    "normalized_form":"STAFF_LETTER",
    "form_role":"event_anchor",
    "ticker":"MDLZ",
    "cik":"0001103982",
    "firm_name":"Mondelez International",
    "industry":"Consumer Staples",
    "thread_id":"MDLZ_0000000000-16-094772",
    "qa_status":"matched_followup_staff_letter",
    "document_name":"filename1.pdf",
    "document_url":"https:\/\/www.sec.gov\/Archives\/edgar\/data\/1103982\/000000000017003205\/filename1.pdf",
    "raw_document_path":"data\/raw\/sec\/MDLZ\/MDLZ_0000000000-16-094772\/filings\/0000000000-17-003205\/filename1.pdf",
    "extracted_text_path":"data\/raw\/sec\/MDLZ\/MDLZ_0000000000-16-094772\/extracted_text\/0000000000-17-003205.txt",
    "extraction_status":"ok",
    "letter_word_count_file":99
  },
  {
    "accessionNumber":"0000000000-17-015933",
    "filingDate":"2017-05-05T00:00:00.000",
    "acceptanceDateTime":"2017-05-05T21:08:31.000Z",
    "form":"UPLOAD",
    "fileNumber":"",
    "primaryDocument":"filename1.pdf",
    "primaryDocDescription":"",
    "isXBRL":0,
    "isInlineXBRL":0,
    "source_file":"company_submissions.json",
    "normalized_form":"STAFF_LETTER",
    "form_role":"event_anchor",
    "ticker":"MDLZ",
    "cik":"0001103982",
    "firm_name":"Mondelez International",
    "industry":"Consumer Staples",
    "thread_id":"MDLZ_0000000000-16-094772",
    "qa_status":"matched_followup_staff_letter",
    "document_name":"filename1.pdf",
    "document_url":"https:\/\/www.sec.gov\/Archives\/edgar\/data\/1103982\/000000000017015933\/filename1.pdf",
    "raw_document_path":"data\/raw\/sec\/MDLZ\/MDLZ_0000000000-16-094772\/filings\/0000000000-17-015933\/filename1.pdf",
    "extracted_text_path":"data\/raw\/sec\/MDLZ\/MDLZ_0000000000-16-094772\/extracted_text\/0000000000-17-015933.txt",
    "extraction_status":"ok",
    "letter_word_count_file":572
  },
  {
    "accessionNumber":"0001193125-17-173542",
    "filingDate":"2017-05-17T00:00:00.000",
    "acceptanceDateTime":"2017-05-17T20:37:02.000Z",
    "form":"CORRESP",
    "fileNumber":"",
    "primaryDocument":"filename1.htm",
    "primaryDocDescription":"",
    "isXBRL":0,
    "isInlineXBRL":0,
    "source_file":"company_submissions.json",
    "normalized_form":"FILER_RESPONSE",
    "form_role":"thread_context",
    "ticker":"MDLZ",
    "cik":"0001103982",
    "firm_name":"Mondelez International",
    "industry":"Consumer Staples",
    "thread_id":"MDLZ_0000000000-16-094772",
    "qa_status":"matched",
    "document_name":"filename1.htm",
    "document_url":"https:\/\/www.sec.gov\/Archives\/edgar\/data\/1103982\/000119312517173542\/filename1.htm",
    "raw_document_path":"data\/raw\/sec\/MDLZ\/MDLZ_0000000000-16-094772\/filings\/0001193125-17-173542\/filename1.htm",
    "extracted_text_path":"data\/raw\/sec\/MDLZ\/MDLZ_0000000000-16-094772\/extracted_text\/0001193125-17-173542.txt",
    "extraction_status":"ok",
    "letter_word_count_file":1208
  },
  {
    "accessionNumber":"0000000000-17-018571",
    "filingDate":"2017-05-26T00:00:00.000",
    "acceptanceDateTime":"2017-05-26T17:48:59.000Z",
    "form":"UPLOAD",
    "fileNumber":"",
    "primaryDocument":"filename1.pdf",
    "primaryDocDescription":"",
    "isXBRL":0,
    "isInlineXBRL":0,
    "source_file":"company_submissions.json",
    "normalized_form":"STAFF_LETTER",
    "form_role":"event_anchor",
    "ticker":"MDLZ",
    "cik":"0001103982",
    "firm_name":"Mondelez International",
    "industry":"Consumer Staples",
    "thread_id":"MDLZ_0000000000-16-094772",
    "qa_status":"matched_followup_staff_letter",
    "document_name":"filename1.pdf",
    "document_url":"https:\/\/www.sec.gov\/Archives\/edgar\/data\/1103982\/000000000017018571\/filename1.pdf",
    "raw_document_path":"data\/raw\/sec\/MDLZ\/MDLZ_0000000000-16-094772\/filings\/0000000000-17-018571\/filename1.pdf",
    "extracted_text_path":"data\/raw\/sec\/MDLZ\/MDLZ_0000000000-16-094772\/extracted_text\/0000000000-17-018571.txt",
    "extraction_status":"ok",
    "letter_word_count_file":126
  }
]