[
  {
    "accessionNumber":"0000000000-23-002523",
    "filingDate":"2023-03-15T00:00:00.000",
    "acceptanceDateTime":"2023-03-15T12:31:08.000Z",
    "form":"UPLOAD",
    "fileNumber":"377-06601",
    "primaryDocument":"filename1.pdf",
    "primaryDocDescription":"",
    "isXBRL":0,
    "isInlineXBRL":0,
    "source_file":"company_submissions.json",
    "normalized_form":"STAFF_LETTER",
    "form_role":"event_anchor",
    "ticker":"SOLV",
    "cik":"0001964738",
    "firm_name":"Solventum",
    "industry":"Health Care",
    "thread_id":"SOLV_0000000000-23-002523",
    "qa_status":"thread_anchor",
    "document_name":"filename1.pdf",
    "document_url":"https:\/\/www.sec.gov\/Archives\/edgar\/data\/1964738\/000000000023002523\/filename1.pdf",
    "raw_document_path":"data\/raw\/sec\/SOLV\/SOLV_0000000000-23-002523\/filings\/0000000000-23-002523\/filename1.pdf",
    "extracted_text_path":"data\/raw\/sec\/SOLV\/SOLV_0000000000-23-002523\/extracted_text\/0000000000-23-002523.txt",
    "extraction_status":"ok",
    "letter_word_count_file":2650
  },
  {
    "accessionNumber":"0000000000-23-005989",
    "filingDate":"2023-06-06T00:00:00.000",
    "acceptanceDateTime":"2023-06-06T07:30:08.000Z",
    "form":"UPLOAD",
    "fileNumber":"377-06601",
    "primaryDocument":"filename1.pdf",
    "primaryDocDescription":"",
    "isXBRL":0,
    "isInlineXBRL":0,
    "source_file":"company_submissions.json",
    "normalized_form":"STAFF_LETTER",
    "form_role":"event_anchor",
    "ticker":"SOLV",
    "cik":"0001964738",
    "firm_name":"Solventum",
    "industry":"Health Care",
    "thread_id":"SOLV_0000000000-23-002523",
    "qa_status":"matched_followup_staff_letter",
    "document_name":"filename1.pdf",
    "document_url":"https:\/\/www.sec.gov\/Archives\/edgar\/data\/1964738\/000000000023005989\/filename1.pdf",
    "raw_document_path":"data\/raw\/sec\/SOLV\/SOLV_0000000000-23-002523\/filings\/0000000000-23-005989\/filename1.pdf",
    "extracted_text_path":"data\/raw\/sec\/SOLV\/SOLV_0000000000-23-002523\/extracted_text\/0000000000-23-005989.txt",
    "extraction_status":"ok",
    "letter_word_count_file":824
  },
  {
    "accessionNumber":"0000000000-23-007285",
    "filingDate":"2023-07-10T00:00:00.000",
    "acceptanceDateTime":"2023-07-10T07:30:07.000Z",
    "form":"UPLOAD",
    "fileNumber":"377-06601",
    "primaryDocument":"filename1.pdf",
    "primaryDocDescription":"",
    "isXBRL":0,
    "isInlineXBRL":0,
    "source_file":"company_submissions.json",
    "normalized_form":"STAFF_LETTER",
    "form_role":"event_anchor",
    "ticker":"SOLV",
    "cik":"0001964738",
    "firm_name":"Solventum",
    "industry":"Health Care",
    "thread_id":"SOLV_0000000000-23-002523",
    "qa_status":"matched_followup_staff_letter",
    "document_name":"filename1.pdf",
    "document_url":"https:\/\/www.sec.gov\/Archives\/edgar\/data\/1964738\/000000000023007285\/filename1.pdf",
    "raw_document_path":"data\/raw\/sec\/SOLV\/SOLV_0000000000-23-002523\/filings\/0000000000-23-007285\/filename1.pdf",
    "extracted_text_path":"data\/raw\/sec\/SOLV\/SOLV_0000000000-23-002523\/extracted_text\/0000000000-23-007285.txt",
    "extraction_status":"ok",
    "letter_word_count_file":1090
  },
  {
    "accessionNumber":"0000000000-23-008764",
    "filingDate":"2023-08-11T00:00:00.000",
    "acceptanceDateTime":"2023-08-11T07:30:07.000Z",
    "form":"UPLOAD",
    "fileNumber":"377-06601",
    "primaryDocument":"filename1.pdf",
    "primaryDocDescription":"",
    "isXBRL":0,
    "isInlineXBRL":0,
    "source_file":"company_submissions.json",
    "normalized_form":"STAFF_LETTER",
    "form_role":"event_anchor",
    "ticker":"SOLV",
    "cik":"0001964738",
    "firm_name":"Solventum",
    "industry":"Health Care",
    "thread_id":"SOLV_0000000000-23-002523",
    "qa_status":"matched_followup_staff_letter",
    "document_name":"filename1.pdf",
    "document_url":"https:\/\/www.sec.gov\/Archives\/edgar\/data\/1964738\/000000000023008764\/filename1.pdf",
    "raw_document_path":"data\/raw\/sec\/SOLV\/SOLV_0000000000-23-002523\/filings\/0000000000-23-008764\/filename1.pdf",
    "extracted_text_path":"data\/raw\/sec\/SOLV\/SOLV_0000000000-23-002523\/extracted_text\/0000000000-23-008764.txt",
    "extraction_status":"ok",
    "letter_word_count_file":765
  }
]