{
  "ticker": "KMI",
  "thread_id": "KMI_0000000000-23-003113",
  "forms_in_thread": [
    "UPLOAD",
    "CORRESP",
    "CORRESP",
    "UPLOAD",
    "CORRESP",
    "UPLOAD"
  ],
  "normalized_forms_in_thread": [
    "STAFF_LETTER",
    "FILER_RESPONSE",
    "FILER_RESPONSE",
    "STAFF_LETTER",
    "FILER_RESPONSE",
    "STAFF_LETTER"
  ],
  "accessions": [
    "0000000000-23-003113",
    "0001506307-23-000032",
    "0001506307-23-000038",
    "0000000000-23-005548",
    "0001506307-23-000052",
    "0000000000-23-006243"
  ],
  "sample_start_date": "2016-01-01",
  "sample_end_date": "2026-04-28"
}