{
  "directory": {
    "item": [
      {
        "last-modified": "2020-01-09 16:20:33",
        "name": "0001193125-20-004711-index-headers.html",
        "type": "text.gif",
        "size": ""
      },
      {
        "last-modified": "2020-01-09 16:20:33",
        "name": "0001193125-20-004711-index.html",
        "type": "text.gif",
        "size": ""
      },
      {
        "last-modified": "2020-01-09 16:20:33",
        "name": "0001193125-20-004711.txt",
        "type": "text.gif",
        "size": ""
      },
      {
        "last-modified": "2020-01-09 16:20:33",
        "name": "filename1.htm",
        "type": "text.gif",
        "size": "9951"
      }
    ],
    "name": "/Archives/edgar/data/1754301/000119312520004711",
    "parent-dir": "/Archives/edgar/data/1754301"
  }
}