{
  "directory": {
    "item": [
      {
        "last-modified": "2017-11-27 16:46:03",
        "name": "0001193125-17-352522-index-headers.html",
        "type": "text.gif",
        "size": ""
      },
      {
        "last-modified": "2017-11-27 16:46:03",
        "name": "0001193125-17-352522-index.html",
        "type": "text.gif",
        "size": ""
      },
      {
        "last-modified": "2017-11-27 16:46:03",
        "name": "0001193125-17-352522.txt",
        "type": "text.gif",
        "size": ""
      },
      {
        "last-modified": "2017-11-27 16:46:03",
        "name": "filename1.htm",
        "type": "text.gif",
        "size": "5937"
      },
      {
        "last-modified": "2017-11-27 16:46:03",
        "name": "g485485g99p75.jpg",
        "type": "image2.gif",
        "size": "2524"
      }
    ],
    "name": "/Archives/edgar/data/1324424/000119312517352522",
    "parent-dir": "/Archives/edgar/data/1324424"
  }
}