{
  "directory": {
    "item": [
      {
        "last-modified": "2017-11-30 17:32:54",
        "name": "0000049196-17-000063-index-headers.html",
        "type": "text.gif",
        "size": ""
      },
      {
        "last-modified": "2017-11-30 17:32:54",
        "name": "0000049196-17-000063-index.html",
        "type": "text.gif",
        "size": ""
      },
      {
        "last-modified": "2017-11-30 17:32:54",
        "name": "0000049196-17-000063.txt",
        "type": "text.gif",
        "size": ""
      },
      {
        "last-modified": "2017-11-30 17:32:54",
        "name": "filename1.htm",
        "type": "text.gif",
        "size": "405705"
      },
      {
        "last-modified": "2017-11-30 17:32:54",
        "name": "huntingtonlogoa07.jpg",
        "type": "image2.gif",
        "size": "10624"
      }
    ],
    "name": "/Archives/edgar/data/49196/000004919617000063",
    "parent-dir": "/Archives/edgar/data/49196"
  }
}